feat/__init__.py
feat/data.py
feat/detector.py
feat/plotting.py
feat/pretrained.py
feat/transforms.py
feat/version.py
feat/au_detectors/__init__.py
feat/au_detectors/StatLearning/SL_test.py
feat/au_detectors/StatLearning/__init__.py
feat/emo_detectors/__init__.py
feat/emo_detectors/ResMaskNet/__init__.py
feat/emo_detectors/ResMaskNet/resmasknet_test.py
feat/emo_detectors/StatLearning/EmoSL_test.py
feat/emo_detectors/StatLearning/__init__.py
feat/face_detectors/__init__.py
feat/face_detectors/FaceBoxes/FaceBoxes_model.py
feat/face_detectors/FaceBoxes/FaceBoxes_test.py
feat/face_detectors/FaceBoxes/__init__.py
feat/face_detectors/MTCNN/MTCNN_model.py
feat/face_detectors/MTCNN/MTCNN_test.py
feat/face_detectors/MTCNN/MTCNN_utils.py
feat/face_detectors/MTCNN/__init__.py
feat/face_detectors/Retinaface/Retinaface_model.py
feat/face_detectors/Retinaface/Retinaface_test.py
feat/face_detectors/Retinaface/Retinaface_utils.py
feat/face_detectors/Retinaface/__init__.py
feat/facepose_detectors/__init__.py
feat/facepose_detectors/img2pose/__init__.py
feat/facepose_detectors/img2pose/img2pose_model.py
feat/facepose_detectors/img2pose/img2pose_test.py
feat/facepose_detectors/img2pose/deps/__init__.py
feat/facepose_detectors/img2pose/deps/generalized_rcnn.py
feat/facepose_detectors/img2pose/deps/image_operations.py
feat/facepose_detectors/img2pose/deps/models.py
feat/facepose_detectors/img2pose/deps/pose_operations.py
feat/facepose_detectors/img2pose/deps/rpn.py
feat/identity_detectors/__init__.py
feat/identity_detectors/facenet/__init__.py
feat/identity_detectors/facenet/facenet_model.py
feat/identity_detectors/facenet/facenet_test.py
feat/landmark_detectors/__init__.py
feat/landmark_detectors/basenet_test.py
feat/landmark_detectors/mobilefacenet_test.py
feat/landmark_detectors/pfld_compressed_test.py
feat/resources/model_list.json
feat/resources/neutral_face_coordinates.csv
feat/tests/__init__.py
feat/tests/conftest.py
feat/tests/test_data.py
feat/tests/test_detector_core.py
py_feat-0.6.2.dist-info/LICENSE
py_feat-0.6.2.dist-info/METADATA
py_feat-0.6.2.dist-info/WHEEL
py_feat-0.6.2.dist-info/top_level.txt
py_feat-0.6.2.dist-info/RECORD
